django_entra_auth/__init__.py
django_entra_auth/backend.py
django_entra_auth/config.py
django_entra_auth/drf_urls.py
django_entra_auth/exceptions.py
django_entra_auth/middleware.py
django_entra_auth/rest_framework.py
django_entra_auth/signals.py
django_entra_auth/urls.py
django_entra_auth/views.py
django_entra_auth/templates/django_entra_auth/login_failed.html
django_entra_auth-1.16.0.dist-info/METADATA
django_entra_auth-1.16.0.dist-info/WHEEL
django_entra_auth-1.16.0.dist-info/licenses/LICENSE
django_entra_auth-1.16.0.dist-info/RECORD
