Metadata-Version: 2.4
Name: django-entra-auth
Version: 1.16.0
Summary: A Django authentication backend for Microsoft Entra ID
Project-URL: Homepage, https://github.com/tnware/django-entra-auth
Project-URL: Repository, https://github.com/tnware/django-entra-auth
Project-URL: Documentation, https://tnware.github.io/django-entra-auth
Author-email: Tyler Woods <tyler@tylermade.net>
Maintainer-email: Tyler Woods <tyler@tylermade.net>
License-Expression: BSD-1-Clause
License-File: LICENSE
Keywords: authentication,azure,django,entra,oidc
Classifier: Development Status :: 5 - Production/Stable
Classifier: Environment :: Web Environment
Classifier: Framework :: Django :: 4.2
Classifier: Framework :: Django :: 5.0
Classifier: Framework :: Django :: 5.1
Classifier: Intended Audience :: Developers
Classifier: Intended Audience :: End Users/Desktop
Classifier: License :: OSI Approved :: BSD License
Classifier: Operating System :: OS Independent
Classifier: Programming Language :: Python
Classifier: Programming Language :: Python :: 3
Classifier: Programming Language :: Python :: 3.9
Classifier: Programming Language :: Python :: 3.10
Classifier: Programming Language :: Python :: 3.11
Classifier: Programming Language :: Python :: 3.12
Classifier: Programming Language :: Python :: 3.13
Classifier: Topic :: Internet :: WWW/HTTP
Classifier: Topic :: Internet :: WWW/HTTP :: Dynamic Content
Classifier: Topic :: Internet :: WWW/HTTP :: WSGI
Classifier: Topic :: Software Development :: Libraries :: Application Frameworks
Classifier: Topic :: Software Development :: Libraries :: Python Modules
Requires-Python: >=3.9
Requires-Dist: cryptography
Requires-Dist: django>=4.2
Requires-Dist: pyjwt
Requires-Dist: requests
Requires-Dist: urllib3
